CHANGES.rst
CONTRIBUTORS.rst
DEVELOP.rst
LICENSE.GPL
LICENSE.rst
MANIFEST.in
README.rst
requirements.txt
setup.cfg
setup.py
docs/index.rst
src/collective/__init__.py
src/collective.testimony.egg-info/PKG-INFO
src/collective.testimony.egg-info/SOURCES.txt
src/collective.testimony.egg-info/dependency_links.txt
src/collective.testimony.egg-info/entry_points.txt
src/collective.testimony.egg-info/namespace_packages.txt
src/collective.testimony.egg-info/not-zip-safe
src/collective.testimony.egg-info/requires.txt
src/collective.testimony.egg-info/top_level.txt
src/collective/testimony/__init__.py
src/collective/testimony/configure.zcml
src/collective/testimony/interfaces.py
src/collective/testimony/permissions.zcml
src/collective/testimony/setuphandlers.py
src/collective/testimony/testing.py
src/collective/testimony/upgrades.py
src/collective/testimony/upgrades.zcml
src/collective/testimony/browser/__init__.py
src/collective/testimony/browser/configure.zcml
src/collective/testimony/browser/overrides/.gitkeep
src/collective/testimony/browser/static/.gitkeep
src/collective/testimony/content/__init__.py
src/collective/testimony/content/configure.zcml
src/collective/testimony/content/testimony.py
src/collective/testimony/content/templates/testimony.pt
src/collective/testimony/locales/collective.testimony.pot
src/collective/testimony/locales/update.sh
src/collective/testimony/locales/fr/LC_MESSAGES/collective.testimony.mo
src/collective/testimony/locales/fr/LC_MESSAGES/collective.testimony.po
src/collective/testimony/profiles/default/browserlayer.xml
src/collective/testimony/profiles/default/catalog.xml
src/collective/testimony/profiles/default/metadata.xml
src/collective/testimony/profiles/default/registry.xml
src/collective/testimony/profiles/default/rolemap.xml
src/collective/testimony/profiles/default/types.xml
src/collective/testimony/profiles/default/types/testimony.xml
src/collective/testimony/profiles/mosaic/browserlayer.xml
src/collective/testimony/profiles/mosaic/metadata.xml
src/collective/testimony/profiles/mosaic/registry.xml
src/collective/testimony/profiles/uninstall/browserlayer.xml
src/collective/testimony/tests/__init__.py
src/collective/testimony/tests/test_robot.py
src/collective/testimony/tests/test_setup.py
src/collective/testimony/tests/robot/test_example.robot
src/collective/testimony/tile/__init__.py
